lightspark/__init__.py
lightspark/exceptions.py
lightspark/lightspark_client.py
lightspark/version.py
lightspark/webhooks.py
lightspark/objects/Account.py
lightspark/objects/AccountToApiTokensConnection.py
lightspark/objects/AccountToChannelsConnection.py
lightspark/objects/AccountToNodesConnection.py
lightspark/objects/AccountToPaymentRequestsConnection.py
lightspark/objects/AccountToTransactionsConnection.py
lightspark/objects/AccountToWalletsConnection.py
lightspark/objects/ApiToken.py
lightspark/objects/Balances.py
lightspark/objects/BitcoinNetwork.py
lightspark/objects/BlockchainBalance.py
lightspark/objects/Channel.py
lightspark/objects/ChannelClosingTransaction.py
lightspark/objects/ChannelFees.py
lightspark/objects/ChannelOpeningTransaction.py
lightspark/objects/ChannelStatus.py
lightspark/objects/ChannelToTransactionsConnection.py
lightspark/objects/CreateApiTokenInput.py
lightspark/objects/CreateApiTokenOutput.py
lightspark/objects/CreateInvoiceInput.py
lightspark/objects/CreateInvoiceOutput.py
lightspark/objects/CreateNodeWalletAddressInput.py
lightspark/objects/CreateNodeWalletAddressOutput.py
lightspark/objects/CurrencyAmount.py
lightspark/objects/CurrencyUnit.py
lightspark/objects/DeleteApiTokenInput.py
lightspark/objects/DeleteApiTokenOutput.py
lightspark/objects/Deposit.py
lightspark/objects/Entity.py
lightspark/objects/FeeEstimate.py
lightspark/objects/FundNodeInput.py
lightspark/objects/FundNodeOutput.py
lightspark/objects/GraphNode.py
lightspark/objects/Hop.py
lightspark/objects/HtlcAttemptFailureCode.py
lightspark/objects/IncomingPayment.py
lightspark/objects/IncomingPaymentAttempt.py
lightspark/objects/IncomingPaymentAttemptStatus.py
lightspark/objects/IncomingPaymentToAttemptsConnection.py
lightspark/objects/Invoice.py
lightspark/objects/InvoiceData.py
lightspark/objects/InvoiceType.py
lightspark/objects/LightningFeeEstimateForInvoiceInput.py
lightspark/objects/LightningFeeEstimateForNodeInput.py
lightspark-1.1.0.dist-info/METADATA
lightspark-1.1.0.dist-info/WHEEL
lightspark-1.1.0.dist-info/top_level.txt
lightspark-1.1.0.dist-info/RECORD
