Metadata-Version: 2.1
Name: lightspark
Version: 1.1.0
Summary: Python SDK for the Lightspark API
Home-page: https://www.lightspark.com/
Author: Lightspark Group, Inc.
Author-email: info@lightspark.com
License: Apache-2.0
Project-URL: Documentation, https://app.lightspark.com/docs/api
Project-URL: Source Code, https://github.com/lightsparkdev/python-sdk
Requires-Dist: cryptography
Requires-Dist: pyjwt
Requires-Dist: requests
